calibtest/__init__.py
calibtest/docs/__init__.py
calibtest/img/stress1.JPG
calibtest/img/workflow.svg
calibtest/moudel/__init__.py
calibtest/moudel/calib_rt.py
calibtest/moudel/datasets.py
calibtest/moudel/regression.py
calibtest/moudel/screen.py
calibtest/moudel/utils.py
calibtest-0.0.6.dist-info/METADATA
calibtest-0.0.6.dist-info/WHEEL
calibtest-0.0.6.dist-info/top_level.txt
calibtest-0.0.6.dist-info/RECORD
