Metadata-Version: 2.1
Name: calibtest
Version: 0.0.6
Summary: A small example package
Home-page: https://github.com/
Author: yiriso
Author-email: kszyc1001@163.com
Classifier: Programming Language :: Python :: 3
Classifier: License :: OSI Approved :: MIT License
Classifier: Operating System :: OS Independent
Requires-Python: >=3
Requires-Dist: numpy
Requires-Dist: pandas
Requires-Dist: networkx
Requires-Dist: statsmodels
Requires-Dist: scipy
